lieparse/__init__.py
lieparse/__main__.py
lieparse/samples/LiepaParse.py
lieparse/samples/__init__.py
lieparse/samples/samples.tar.gz
lieparse-1.1.0.dist-info/METADATA
lieparse-1.1.0.dist-info/WHEEL
lieparse-1.1.0.dist-info/entry_points.txt
lieparse-1.1.0.dist-info/top_level.txt
lieparse-1.1.0.dist-info/RECORD
