Metadata-Version: 2.1
Name: lieparse
Version: 1.1.0
Summary: HTML parser ant text retriever using user defined rule set
Home-page: https://pypi.org/project/lieparse/
Author: Vidmantas Balčytis
Author-email: vidma@lema.lt
License: UNKNOWN
Keywords: html parser
Platform: UNKNOWN
Classifier: Development Status :: 5 - Production/Stable
Classifier: Environment :: Console
Classifier: Environment :: Web Environment
Classifier: Intended Audience :: End Users/Desktop
Classifier: Intended Audience :: Developers
Classifier: Topic :: Internet :: WWW/HTTP :: Indexing/Search
Classifier: License :: OSI Approved :: Python Software Foundation License
Classifier: Operating System :: Microsoft :: Windows
Classifier: Operating System :: POSIX
Classifier: Programming Language :: Python :: 3 :: Only
Requires-Python: >=3.5
Requires-Dist: regex
Requires-Dist: rst2ansi
